EvolutionaryFS.py
EvolutionaryFS-0.0.5.dist-info/LICENSE
EvolutionaryFS-0.0.5.dist-info/METADATA
EvolutionaryFS-0.0.5.dist-info/WHEEL
EvolutionaryFS-0.0.5.dist-info/top_level.txt
EvolutionaryFS-0.0.5.dist-info/RECORD
