Metadata-Version: 2.1
Name: EvolutionaryFS
Version: 0.0.5
Summary: Implementation of evolutionary algorithm for machine learning feature selection
Home-page: https://github.com/StatguyUser/EvolutionaryFS
Author: StatguyUser
License: UNKNOWN
Download-URL: https://github.com/EvolutionaryFS/EvolutionaryFS.git
Platform: UNKNOWN
Requires-Dist: numpy
